windows_control-0.0.10.dist-info/METADATA
windows_control-0.0.10.dist-info/WHEEL
windows_control/__init__.py
windows_control/windows_control.pyd
windows_control-0.0.10.dist-info/RECORD
