Metadata-Version: 2.4
Name: windows_control
Version: 0.0.10
Classifier: Programming Language :: Rust
Classifier: Programming Language :: Python :: Implementation :: CPython
Classifier: Programming Language :: Python :: Implementation :: PyPy
Summary: It is used to do some control with keyboard/mouse on windows (especially on win10).
Requires-Python: >=3.8
Project-URL: repository, https://github.com/dbsxdbsx/windows_control
